crmify
